aroma/__init__.py
aroma/datasets/__init__.py
aroma/datasets/breakfast.py
aroma/preprocessing/__init__.py
aroma/preprocessing/intertimes.py
aroma/testing.py
aroma/utils/__init__.py
aroma/utils/download.py
aroma/utils/imports.py
aroma/utils/vocab.py
aroma-0.0.0a7.dist-info/LICENSE
aroma-0.0.0a7.dist-info/METADATA
aroma-0.0.0a7.dist-info/WHEEL
aroma-0.0.0a7.dist-info/RECORD
